ckanext_Dataset_Reference-2.0.1-nspkg.pth
ckanext/dataset_reference/__init__.py
ckanext/dataset_reference/plugin.py
ckanext/dataset_reference/public/statics/add_manually.css
ckanext/dataset_reference/public/statics/add_manually.js
ckanext/dataset_reference/public/statics/add_reference.css
ckanext/dataset_reference/public/statics/add_reference.js
ckanext/dataset_reference/public/statics/publication_info.css
ckanext/dataset_reference/public/statics/publication_info_table.js
ckanext/dataset_reference/templates/add_manually.html
ckanext/dataset_reference/templates/package/read.html
ckanext/dataset_reference/templates/package/read_base.html
ckanext/dataset_reference/templates/snippets/link_publication.html
ckanext/dataset_reference/templates/snippets/publication_info.html
ckanext/dataset_reference/tests/__init__.py
ckanext/dataset_reference/tests/test_controller.py
ckanext/dataset_reference/tests/test_lib.py
ckanext/dataset_reference/tests/test_plugin.py
ckanext_Dataset_Reference-2.0.1.dist-info/LICENSE
ckanext_Dataset_Reference-2.0.1.dist-info/METADATA
ckanext_Dataset_Reference-2.0.1.dist-info/WHEEL
ckanext_Dataset_Reference-2.0.1.dist-info/entry_points.txt
ckanext_Dataset_Reference-2.0.1.dist-info/namespace_packages.txt
ckanext_Dataset_Reference-2.0.1.dist-info/top_level.txt
ckanext_Dataset_Reference-2.0.1.dist-info/RECORD
