Metadata-Version: 2.1
Name: ckanext-Dataset-Reference
Version: 2.0.1
Summary: This CKAN extension ables CKAN users to link references to their dataset. A reference can be a publication or another dataset. The extension embeds the added references to the target dataset view as a table of citations.
Home-page: https://github.com/TIBHannover/ckanext-Dataset-Reference
Author: Pooya Oladazimi, Technische Informationsbibliothek(TIB)
Author-email: pooya.oladazimi@tib.eu
License: AGPL
Keywords: CKAN
Platform: UNKNOWN
Classifier: Development Status :: 3 - Alpha
Classifier: License :: OSI Approved :: GNU Affero General Public License v3 or later (AGPLv3+)
Classifier: Programming Language :: Python :: 3
